deploy_pkg/__main__.py
deploy_pkg-0.0.12.dist-info/licenses/LICENSE
deploy_pkg-0.0.12.dist-info/METADATA
deploy_pkg-0.0.12.dist-info/WHEEL
deploy_pkg-0.0.12.dist-info/entry_points.txt
deploy_pkg-0.0.12.dist-info/top_level.txt
deploy_pkg-0.0.12.dist-info/RECORD
