Metadata-Version: 2.4
Name: deploy_pkg
Version: 0.0.12
Summary: One-shot bootstrap & deploy script for Python packages (git+GitHub+PyPI).
Author-email: Baptiste Ferrand <bferrand.maths@gmail.com>
License: MIT
Requires-Python: >=3.8
License-File: LICENSE
Requires-Dist: toml>=0.10
Requires-Dist: requests>=2
Requires-Dist: python-dotenv>=1
Dynamic: license-file
